[{"strike": 450, "type": "PUT", "ticker": "O:QQQ250625P00450000", "expiry": "2025-06-25"}, {"strike": 451, "type": "PUT", "ticker": "O:QQQ250625P00451000", "expiry": "2025-06-25"}, {"strike": 452, "type": "PUT", "ticker": "O:QQQ250625P00452000", "expiry": "2025-06-25"}, {"strike": 453, "type": "PUT", "ticker": "O:QQQ250625P00453000", "expiry": "2025-06-25"}, {"strike": 454, "type": "PUT", "ticker": "O:QQQ250625P00454000", "expiry": "2025-06-25"}, {"strike": 455, "type": "PUT", "ticker": "O:QQQ250625P00455000", "expiry": "2025-06-25"}, {"strike": 456, "type": "PUT", "ticker": "O:QQQ250625P00456000", "expiry": "2025-06-25"}, {"strike": 457, "type": "PUT", "ticker": "O:QQQ250625P00457000", "expiry": "2025-06-25"}, {"strike": 458, "type": "PUT", "ticker": "O:QQQ250625P00458000", "expiry": "2025-06-25"}, {"strike": 459, "type": "PUT", "ticker": "O:QQQ250625P00459000", "expiry": "2025-06-25"}, {"strike": 460, "type": "PUT", "ticker": "O:QQQ250625P00460000", "expiry": "2025-06-25"}, {"strike": 461, "type": "PUT", "ticker": "O:QQQ250625P00461000", "expiry": "2025-06-25"}, {"strike": 462, "type": "PUT", "ticker": "O:QQQ250625P00462000", "expiry": "2025-06-25"}, {"strike": 463, "type": "PUT", "ticker": "O:QQQ250625P00463000", "expiry": "2025-06-25"}, {"strike": 464, "type": "PUT", "ticker": "O:QQQ250625P00464000", "expiry": "2025-06-25"}, {"strike": 465, "type": "PUT", "ticker": "O:QQQ250625P00465000", "expiry": "2025-06-25"}, {"strike": 466, "type": "PUT", "ticker": "O:QQQ250625P00466000", "expiry": "2025-06-25"}, {"strike": 467, "type": "PUT", "ticker": "O:QQQ250625P00467000", "expiry": "2025-06-25"}, {"strike": 468, "type": "PUT", "ticker": "O:QQQ250625P00468000", "expiry": "2025-06-25"}, {"strike": 469, "type": "PUT", "ticker": "O:QQQ250625P00469000", "expiry": "2025-06-25"}, {"strike": 470, "type": "PUT", "ticker": "O:QQQ250625P00470000", "expiry": "2025-06-25"}, {"strike": 471, "type": "PUT", "ticker": "O:QQQ250625P00471000", "expiry": "2025-06-25"}, {"strike": 472, "type": "PUT", "ticker": "O:QQQ250625P00472000", "expiry": "2025-06-25"}, {"strike": 473, "type": "PUT", "ticker": "O:QQQ250625P00473000", "expiry": "2025-06-25"}, {"strike": 474, "type": "PUT", "ticker": "O:QQQ250625P00474000", "expiry": "2025-06-25"}, {"strike": 475, "type": "PUT", "ticker": "O:QQQ250625P00475000", "expiry": "2025-06-25"}, {"strike": 476, "type": "PUT", "ticker": "O:QQQ250625P00476000", "expiry": "2025-06-25"}, {"strike": 477, "type": "PUT", "ticker": "O:QQQ250625P00477000", "expiry": "2025-06-25"}, {"strike": 478, "type": "PUT", "ticker": "O:QQQ250625P00478000", "expiry": "2025-06-25"}, {"strike": 479, "type": "PUT", "ticker": "O:QQQ250625P00479000", "expiry": "2025-06-25"}, {"strike": 480, "type": "PUT", "ticker": "O:QQQ250625P00480000", "expiry": "2025-06-25"}, {"strike": 481, "type": "PUT", "ticker": "O:QQQ250625P00481000", "expiry": "2025-06-25"}, {"strike": 482, "type": "PUT", "ticker": "O:QQQ250625P00482000", "expiry": "2025-06-25"}, {"strike": 483, "type": "PUT", "ticker": "O:QQQ250625P00483000", "expiry": "2025-06-25"}, {"strike": 484, "type": "PUT", "ticker": "O:QQQ250625P00484000", "expiry": "2025-06-25"}, {"strike": 485, "type": "PUT", "ticker": "O:QQQ250625P00485000", "expiry": "2025-06-25"}, {"strike": 486, "type": "PUT", "ticker": "O:QQQ250625P00486000", "expiry": "2025-06-25"}, {"strike": 487, "type": "PUT", "ticker": "O:QQQ250625P00487000", "expiry": "2025-06-25"}, {"strike": 488, "type": "PUT", "ticker": "O:QQQ250625P00488000", "expiry": "2025-06-25"}, {"strike": 489, "type": "PUT", "ticker": "O:QQQ250625P00489000", "expiry": "2025-06-25"}, {"strike": 490, "type": "PUT", "ticker": "O:QQQ250625P00490000", "expiry": "2025-06-25"}, {"strike": 491, "type": "PUT", "ticker": "O:QQQ250625P00491000", "expiry": "2025-06-25"}, {"strike": 492, "type": "PUT", "ticker": "O:QQQ250625P00492000", "expiry": "2025-06-25"}, {"strike": 493, "type": "PUT", "ticker": "O:QQQ250625P00493000", "expiry": "2025-06-25"}, {"strike": 494, "type": "PUT", "ticker": "O:QQQ250625P00494000", "expiry": "2025-06-25"}, {"strike": 495, "type": "PUT", "ticker": "O:QQQ250625P00495000", "expiry": "2025-06-25"}, {"strike": 496, "type": "PUT", "ticker": "O:QQQ250625P00496000", "expiry": "2025-06-25"}, {"strike": 497, "type": "PUT", "ticker": "O:QQQ250625P00497000", "expiry": "2025-06-25"}, {"strike": 498, "type": "PUT", "ticker": "O:QQQ250625P00498000", "expiry": "2025-06-25"}, {"strike": 499, "type": "PUT", "ticker": "O:QQQ250625P00499000", "expiry": "2025-06-25"}, {"strike": 500, "type": "PUT", "ticker": "O:QQQ250625P00500000", "expiry": "2025-06-25"}, {"strike": 501, "type": "PUT", "ticker": "O:QQQ250625P00501000", "expiry": "2025-06-25"}, {"strike": 502, "type": "PUT", "ticker": "O:QQQ250625P00502000", "expiry": "2025-06-25"}, {"strike": 503, "type": "PUT", "ticker": "O:QQQ250625P00503000", "expiry": "2025-06-25"}, {"strike": 504, "type": "PUT", "ticker": "O:QQQ250625P00504000", "expiry": "2025-06-25"}, {"strike": 505, "type": "PUT", "ticker": "O:QQQ250625P00505000", "expiry": "2025-06-25"}, {"strike": 506, "type": "PUT", "ticker": "O:QQQ250625P00506000", "expiry": "2025-06-25"}, {"strike": 507, "type": "PUT", "ticker": "O:QQQ250625P00507000", "expiry": "2025-06-25"}, {"strike": 508, "type": "PUT", "ticker": "O:QQQ250625P00508000", "expiry": "2025-06-25"}, {"strike": 509, "type": "PUT", "ticker": "O:QQQ250625P00509000", "expiry": "2025-06-25"}, {"strike": 510, "type": "PUT", "ticker": "O:QQQ250625P00510000", "expiry": "2025-06-25"}, {"strike": 511, "type": "PUT", "ticker": "O:QQQ250625P00511000", "expiry": "2025-06-25"}, {"strike": 512, "type": "PUT", "ticker": "O:QQQ250625P00512000", "expiry": "2025-06-25"}, {"strike": 513, "type": "PUT", "ticker": "O:QQQ250625P00513000", "expiry": "2025-06-25"}, {"strike": 514, "type": "PUT", "ticker": "O:QQQ250625P00514000", "expiry": "2025-06-25"}, {"strike": 515, "type": "PUT", "ticker": "O:QQQ250625P00515000", "expiry": "2025-06-25"}, {"strike": 516, "type": "PUT", "ticker": "O:QQQ250625P00516000", "expiry": "2025-06-25"}, {"strike": 517, "type": "PUT", "ticker": "O:QQQ250625P00517000", "expiry": "2025-06-25"}, {"strike": 518, "type": "PUT", "ticker": "O:QQQ250625P00518000", "expiry": "2025-06-25"}, {"strike": 519, "type": "PUT", "ticker": "O:QQQ250625P00519000", "expiry": "2025-06-25"}, {"strike": 520, "type": "PUT", "ticker": "O:QQQ250625P00520000", "expiry": "2025-06-25"}, {"strike": 521, "type": "PUT", "ticker": "O:QQQ250625P00521000", "expiry": "2025-06-25"}, {"strike": 522, "type": "PUT", "ticker": "O:QQQ250625P00522000", "expiry": "2025-06-25"}, {"strike": 523, "type": "PUT", "ticker": "O:QQQ250625P00523000", "expiry": "2025-06-25"}, {"strike": 524, "type": "PUT", "ticker": "O:QQQ250625P00524000", "expiry": "2025-06-25"}, {"strike": 525, "type": "PUT", "ticker": "O:QQQ250625P00525000", "expiry": "2025-06-25"}, {"strike": 526, "type": "PUT", "ticker": "O:QQQ250625P00526000", "expiry": "2025-06-25"}, {"strike": 527, "type": "PUT", "ticker": "O:QQQ250625P00527000", "expiry": "2025-06-25"}, {"strike": 528, "type": "PUT", "ticker": "O:QQQ250625P00528000", "expiry": "2025-06-25"}, {"strike": 529, "type": "PUT", "ticker": "O:QQQ250625P00529000", "expiry": "2025-06-25"}, {"strike": 530, "type": "PUT", "ticker": "O:QQQ250625P00530000", "expiry": "2025-06-25"}, {"strike": 531, "type": "PUT", "ticker": "O:QQQ250625P00531000", "expiry": "2025-06-25"}, {"strike": 532, "type": "PUT", "ticker": "O:QQQ250625P00532000", "expiry": "2025-06-25"}, {"strike": 533, "type": "PUT", "ticker": "O:QQQ250625P00533000", "expiry": "2025-06-25"}, {"strike": 534, "type": "PUT", "ticker": "O:QQQ250625P00534000", "expiry": "2025-06-25"}, {"strike": 535, "type": "PUT", "ticker": "O:QQQ250625P00535000", "expiry": "2025-06-25"}, {"strike": 536, "type": "PUT", "ticker": "O:QQQ250625P00536000", "expiry": "2025-06-25"}, {"strike": 537, "type": "PUT", "ticker": "O:QQQ250625P00537000", "expiry": "2025-06-25"}, {"strike": 538, "type": "PUT", "ticker": "O:QQQ250625P00538000", "expiry": "2025-06-25"}, {"strike": 539, "type": "PUT", "ticker": "O:QQQ250625P00539000", "expiry": "2025-06-25"}, {"strike": 540, "type": "PUT", "ticker": "O:QQQ250625P00540000", "expiry": "2025-06-25"}, {"strike": 541, "type": "PUT", "ticker": "O:QQQ250625P00541000", "expiry": "2025-06-25"}, {"strike": 542, "type": "PUT", "ticker": "O:QQQ250625P00542000", "expiry": "2025-06-25"}, {"strike": 543, "type": "PUT", "ticker": "O:QQQ250625P00543000", "expiry": "2025-06-25"}, {"strike": 544, "type": "PUT", "ticker": "O:QQQ250625P00544000", "expiry": "2025-06-25"}, {"strike": 545, "type": "PUT", "ticker": "O:QQQ250625P00545000", "expiry": "2025-06-25"}, {"strike": 546, "type": "PUT", "ticker": "O:QQQ250625P00546000", "expiry": "2025-06-25"}, {"strike": 547, "type": "PUT", "ticker": "O:QQQ250625P00547000", "expiry": "2025-06-25"}, {"strike": 548, "type": "PUT", "ticker": "O:QQQ250625P00548000", "expiry": "2025-06-25"}, {"strike": 549, "type": "PUT", "ticker": "O:QQQ250625P00549000", "expiry": "2025-06-25"}, {"strike": 550, "type": "PUT", "ticker": "O:QQQ250625P00550000", "expiry": "2025-06-25"}, {"strike": 555, "type": "PUT", "ticker": "O:QQQ250625P00555000", "expiry": "2025-06-25"}, {"strike": 560, "type": "PUT", "ticker": "O:QQQ250625P00560000", "expiry": "2025-06-25"}, {"strike": 565, "type": "PUT", "ticker": "O:QQQ250625P00565000", "expiry": "2025-06-25"}, {"strike": 570, "type": "PUT", "ticker": "O:QQQ250625P00570000", "expiry": "2025-06-25"}, {"strike": 575, "type": "PUT", "ticker": "O:QQQ250625P00575000", "expiry": "2025-06-25"}, {"strike": 580, "type": "PUT", "ticker": "O:QQQ250625P00580000", "expiry": "2025-06-25"}, {"strike": 585, "type": "PUT", "ticker": "O:QQQ250625P00585000", "expiry": "2025-06-25"}, {"strike": 590, "type": "PUT", "ticker": "O:QQQ250625P00590000", "expiry": "2025-06-25"}, {"strike": 595, "type": "PUT", "ticker": "O:QQQ250625P00595000", "expiry": "2025-06-25"}, {"strike": 600, "type": "PUT", "ticker": "O:QQQ250625P00600000", "expiry": "2025-06-25"}, {"strike": 605, "type": "PUT", "ticker": "O:QQQ250625P00605000", "expiry": "2025-06-25"}, {"strike": 610, "type": "PUT", "ticker": "O:QQQ250625P00610000", "expiry": "2025-06-25"}]