[{"strike": 408, "type": "PUT", "ticker": "O:QQQ241007P00408000", "expiry": "2024-10-07"}, {"strike": 409, "type": "PUT", "ticker": "O:QQQ241007P00409000", "expiry": "2024-10-07"}, {"strike": 410, "type": "PUT", "ticker": "O:QQQ241007P00410000", "expiry": "2024-10-07"}, {"strike": 411, "type": "PUT", "ticker": "O:QQQ241007P00411000", "expiry": "2024-10-07"}, {"strike": 412, "type": "PUT", "ticker": "O:QQQ241007P00412000", "expiry": "2024-10-07"}, {"strike": 413, "type": "PUT", "ticker": "O:QQQ241007P00413000", "expiry": "2024-10-07"}, {"strike": 414, "type": "PUT", "ticker": "O:QQQ241007P00414000", "expiry": "2024-10-07"}, {"strike": 415, "type": "PUT", "ticker": "O:QQQ241007P00415000", "expiry": "2024-10-07"}, {"strike": 416, "type": "PUT", "ticker": "O:QQQ241007P00416000", "expiry": "2024-10-07"}, {"strike": 417, "type": "PUT", "ticker": "O:QQQ241007P00417000", "expiry": "2024-10-07"}, {"strike": 418, "type": "PUT", "ticker": "O:QQQ241007P00418000", "expiry": "2024-10-07"}, {"strike": 419, "type": "PUT", "ticker": "O:QQQ241007P00419000", "expiry": "2024-10-07"}, {"strike": 420, "type": "PUT", "ticker": "O:QQQ241007P00420000", "expiry": "2024-10-07"}, {"strike": 421, "type": "PUT", "ticker": "O:QQQ241007P00421000", "expiry": "2024-10-07"}, {"strike": 422, "type": "PUT", "ticker": "O:QQQ241007P00422000", "expiry": "2024-10-07"}, {"strike": 423, "type": "PUT", "ticker": "O:QQQ241007P00423000", "expiry": "2024-10-07"}, {"strike": 424, "type": "PUT", "ticker": "O:QQQ241007P00424000", "expiry": "2024-10-07"}, {"strike": 425, "type": "PUT", "ticker": "O:QQQ241007P00425000", "expiry": "2024-10-07"}, {"strike": 426, "type": "PUT", "ticker": "O:QQQ241007P00426000", "expiry": "2024-10-07"}, {"strike": 427, "type": "PUT", "ticker": "O:QQQ241007P00427000", "expiry": "2024-10-07"}, {"strike": 428, "type": "PUT", "ticker": "O:QQQ241007P00428000", "expiry": "2024-10-07"}, {"strike": 429, "type": "PUT", "ticker": "O:QQQ241007P00429000", "expiry": "2024-10-07"}, {"strike": 430, "type": "PUT", "ticker": "O:QQQ241007P00430000", "expiry": "2024-10-07"}, {"strike": 431, "type": "PUT", "ticker": "O:QQQ241007P00431000", "expiry": "2024-10-07"}, {"strike": 432, "type": "PUT", "ticker": "O:QQQ241007P00432000", "expiry": "2024-10-07"}, {"strike": 433, "type": "PUT", "ticker": "O:QQQ241007P00433000", "expiry": "2024-10-07"}, {"strike": 434, "type": "PUT", "ticker": "O:QQQ241007P00434000", "expiry": "2024-10-07"}, {"strike": 435, "type": "PUT", "ticker": "O:QQQ241007P00435000", "expiry": "2024-10-07"}, {"strike": 436, "type": "PUT", "ticker": "O:QQQ241007P00436000", "expiry": "2024-10-07"}, {"strike": 437, "type": "PUT", "ticker": "O:QQQ241007P00437000", "expiry": "2024-10-07"}, {"strike": 438, "type": "PUT", "ticker": "O:QQQ241007P00438000", "expiry": "2024-10-07"}, {"strike": 439, "type": "PUT", "ticker": "O:QQQ241007P00439000", "expiry": "2024-10-07"}, {"strike": 440, "type": "PUT", "ticker": "O:QQQ241007P00440000", "expiry": "2024-10-07"}, {"strike": 441, "type": "PUT", "ticker": "O:QQQ241007P00441000", "expiry": "2024-10-07"}, {"strike": 442, "type": "PUT", "ticker": "O:QQQ241007P00442000", "expiry": "2024-10-07"}, {"strike": 443, "type": "PUT", "ticker": "O:QQQ241007P00443000", "expiry": "2024-10-07"}, {"strike": 444, "type": "PUT", "ticker": "O:QQQ241007P00444000", "expiry": "2024-10-07"}, {"strike": 445, "type": "PUT", "ticker": "O:QQQ241007P00445000", "expiry": "2024-10-07"}, {"strike": 446, "type": "PUT", "ticker": "O:QQQ241007P00446000", "expiry": "2024-10-07"}, {"strike": 447, "type": "PUT", "ticker": "O:QQQ241007P00447000", "expiry": "2024-10-07"}, {"strike": 448, "type": "PUT", "ticker": "O:QQQ241007P00448000", "expiry": "2024-10-07"}, {"strike": 449, "type": "PUT", "ticker": "O:QQQ241007P00449000", "expiry": "2024-10-07"}, {"strike": 450, "type": "PUT", "ticker": "O:QQQ241007P00450000", "expiry": "2024-10-07"}, {"strike": 451, "type": "PUT", "ticker": "O:QQQ241007P00451000", "expiry": "2024-10-07"}, {"strike": 452, "type": "PUT", "ticker": "O:QQQ241007P00452000", "expiry": "2024-10-07"}, {"strike": 453, "type": "PUT", "ticker": "O:QQQ241007P00453000", "expiry": "2024-10-07"}, {"strike": 454, "type": "PUT", "ticker": "O:QQQ241007P00454000", "expiry": "2024-10-07"}, {"strike": 455, "type": "PUT", "ticker": "O:QQQ241007P00455000", "expiry": "2024-10-07"}, {"strike": 456, "type": "PUT", "ticker": "O:QQQ241007P00456000", "expiry": "2024-10-07"}, {"strike": 457, "type": "PUT", "ticker": "O:QQQ241007P00457000", "expiry": "2024-10-07"}, {"strike": 458, "type": "PUT", "ticker": "O:QQQ241007P00458000", "expiry": "2024-10-07"}, {"strike": 459, "type": "PUT", "ticker": "O:QQQ241007P00459000", "expiry": "2024-10-07"}, {"strike": 460, "type": "PUT", "ticker": "O:QQQ241007P00460000", "expiry": "2024-10-07"}, {"strike": 461, "type": "PUT", "ticker": "O:QQQ241007P00461000", "expiry": "2024-10-07"}, {"strike": 462, "type": "PUT", "ticker": "O:QQQ241007P00462000", "expiry": "2024-10-07"}, {"strike": 463, "type": "PUT", "ticker": "O:QQQ241007P00463000", "expiry": "2024-10-07"}, {"strike": 464, "type": "PUT", "ticker": "O:QQQ241007P00464000", "expiry": "2024-10-07"}, {"strike": 465, "type": "PUT", "ticker": "O:QQQ241007P00465000", "expiry": "2024-10-07"}, {"strike": 466, "type": "PUT", "ticker": "O:QQQ241007P00466000", "expiry": "2024-10-07"}, {"strike": 467, "type": "PUT", "ticker": "O:QQQ241007P00467000", "expiry": "2024-10-07"}, {"strike": 468, "type": "PUT", "ticker": "O:QQQ241007P00468000", "expiry": "2024-10-07"}, {"strike": 469, "type": "PUT", "ticker": "O:QQQ241007P00469000", "expiry": "2024-10-07"}, {"strike": 470, "type": "PUT", "ticker": "O:QQQ241007P00470000", "expiry": "2024-10-07"}, {"strike": 471, "type": "PUT", "ticker": "O:QQQ241007P00471000", "expiry": "2024-10-07"}, {"strike": 472, "type": "PUT", "ticker": "O:QQQ241007P00472000", "expiry": "2024-10-07"}, {"strike": 473, "type": "PUT", "ticker": "O:QQQ241007P00473000", "expiry": "2024-10-07"}, {"strike": 474, "type": "PUT", "ticker": "O:QQQ241007P00474000", "expiry": "2024-10-07"}, {"strike": 475, "type": "PUT", "ticker": "O:QQQ241007P00475000", "expiry": "2024-10-07"}, {"strike": 476, "type": "PUT", "ticker": "O:QQQ241007P00476000", "expiry": "2024-10-07"}, {"strike": 477, "type": "PUT", "ticker": "O:QQQ241007P00477000", "expiry": "2024-10-07"}, {"strike": 478, "type": "PUT", "ticker": "O:QQQ241007P00478000", "expiry": "2024-10-07"}, {"strike": 479, "type": "PUT", "ticker": "O:QQQ241007P00479000", "expiry": "2024-10-07"}, {"strike": 480, "type": "PUT", "ticker": "O:QQQ241007P00480000", "expiry": "2024-10-07"}, {"strike": 481, "type": "PUT", "ticker": "O:QQQ241007P00481000", "expiry": "2024-10-07"}, {"strike": 482, "type": "PUT", "ticker": "O:QQQ241007P00482000", "expiry": "2024-10-07"}, {"strike": 483, "type": "PUT", "ticker": "O:QQQ241007P00483000", "expiry": "2024-10-07"}, {"strike": 484, "type": "PUT", "ticker": "O:QQQ241007P00484000", "expiry": "2024-10-07"}, {"strike": 485, "type": "PUT", "ticker": "O:QQQ241007P00485000", "expiry": "2024-10-07"}, {"strike": 486, "type": "PUT", "ticker": "O:QQQ241007P00486000", "expiry": "2024-10-07"}, {"strike": 487, "type": "PUT", "ticker": "O:QQQ241007P00487000", "expiry": "2024-10-07"}, {"strike": 488, "type": "PUT", "ticker": "O:QQQ241007P00488000", "expiry": "2024-10-07"}, {"strike": 489, "type": "PUT", "ticker": "O:QQQ241007P00489000", "expiry": "2024-10-07"}, {"strike": 490, "type": "PUT", "ticker": "O:QQQ241007P00490000", "expiry": "2024-10-07"}, {"strike": 491, "type": "PUT", "ticker": "O:QQQ241007P00491000", "expiry": "2024-10-07"}, {"strike": 492, "type": "PUT", "ticker": "O:QQQ241007P00492000", "expiry": "2024-10-07"}, {"strike": 493, "type": "PUT", "ticker": "O:QQQ241007P00493000", "expiry": "2024-10-07"}, {"strike": 494, "type": "PUT", "ticker": "O:QQQ241007P00494000", "expiry": "2024-10-07"}, {"strike": 495, "type": "PUT", "ticker": "O:QQQ241007P00495000", "expiry": "2024-10-07"}, {"strike": 496, "type": "PUT", "ticker": "O:QQQ241007P00496000", "expiry": "2024-10-07"}, {"strike": 497, "type": "PUT", "ticker": "O:QQQ241007P00497000", "expiry": "2024-10-07"}, {"strike": 498, "type": "PUT", "ticker": "O:QQQ241007P00498000", "expiry": "2024-10-07"}, {"strike": 499, "type": "PUT", "ticker": "O:QQQ241007P00499000", "expiry": "2024-10-07"}, {"strike": 500, "type": "PUT", "ticker": "O:QQQ241007P00500000", "expiry": "2024-10-07"}, {"strike": 501, "type": "PUT", "ticker": "O:QQQ241007P00501000", "expiry": "2024-10-07"}, {"strike": 502, "type": "PUT", "ticker": "O:QQQ241007P00502000", "expiry": "2024-10-07"}, {"strike": 503, "type": "PUT", "ticker": "O:QQQ241007P00503000", "expiry": "2024-10-07"}, {"strike": 504, "type": "PUT", "ticker": "O:QQQ241007P00504000", "expiry": "2024-10-07"}, {"strike": 505, "type": "PUT", "ticker": "O:QQQ241007P00505000", "expiry": "2024-10-07"}, {"strike": 506, "type": "PUT", "ticker": "O:QQQ241007P00506000", "expiry": "2024-10-07"}, {"strike": 507, "type": "PUT", "ticker": "O:QQQ241007P00507000", "expiry": "2024-10-07"}, {"strike": 508, "type": "PUT", "ticker": "O:QQQ241007P00508000", "expiry": "2024-10-07"}, {"strike": 509, "type": "PUT", "ticker": "O:QQQ241007P00509000", "expiry": "2024-10-07"}, {"strike": 510, "type": "PUT", "ticker": "O:QQQ241007P00510000", "expiry": "2024-10-07"}, {"strike": 515, "type": "PUT", "ticker": "O:QQQ241007P00515000", "expiry": "2024-10-07"}, {"strike": 520, "type": "PUT", "ticker": "O:QQQ241007P00520000", "expiry": "2024-10-07"}, {"strike": 525, "type": "PUT", "ticker": "O:QQQ241007P00525000", "expiry": "2024-10-07"}, {"strike": 530, "type": "PUT", "ticker": "O:QQQ241007P00530000", "expiry": "2024-10-07"}, {"strike": 535, "type": "PUT", "ticker": "O:QQQ241007P00535000", "expiry": "2024-10-07"}, {"strike": 540, "type": "PUT", "ticker": "O:QQQ241007P00540000", "expiry": "2024-10-07"}, {"strike": 545, "type": "PUT", "ticker": "O:QQQ241007P00545000", "expiry": "2024-10-07"}, {"strike": 550, "type": "PUT", "ticker": "O:QQQ241007P00550000", "expiry": "2024-10-07"}, {"strike": 555, "type": "PUT", "ticker": "O:QQQ241007P00555000", "expiry": "2024-10-07"}, {"strike": 560, "type": "PUT", "ticker": "O:QQQ241007P00560000", "expiry": "2024-10-07"}]