[{"strike": 250, "type": "CALL", "ticker": "O:SPY250501C00250000", "expiry": "2025-05-01"}, {"strike": 255, "type": "CALL", "ticker": "O:SPY250501C00255000", "expiry": "2025-05-01"}, {"strike": 260, "type": "CALL", "ticker": "O:SPY250501C00260000", "expiry": "2025-05-01"}, {"strike": 265, "type": "CALL", "ticker": "O:SPY250501C00265000", "expiry": "2025-05-01"}, {"strike": 270, "type": "CALL", "ticker": "O:SPY250501C00270000", "expiry": "2025-05-01"}, {"strike": 275, "type": "CALL", "ticker": "O:SPY250501C00275000", "expiry": "2025-05-01"}, {"strike": 280, "type": "CALL", "ticker": "O:SPY250501C00280000", "expiry": "2025-05-01"}, {"strike": 285, "type": "CALL", "ticker": "O:SPY250501C00285000", "expiry": "2025-05-01"}, {"strike": 290, "type": "CALL", "ticker": "O:SPY250501C00290000", "expiry": "2025-05-01"}, {"strike": 295, "type": "CALL", "ticker": "O:SPY250501C00295000", "expiry": "2025-05-01"}, {"strike": 300, "type": "CALL", "ticker": "O:SPY250501C00300000", "expiry": "2025-05-01"}, {"strike": 305, "type": "CALL", "ticker": "O:SPY250501C00305000", "expiry": "2025-05-01"}, {"strike": 310, "type": "CALL", "ticker": "O:SPY250501C00310000", "expiry": "2025-05-01"}, {"strike": 315, "type": "CALL", "ticker": "O:SPY250501C00315000", "expiry": "2025-05-01"}, {"strike": 320, "type": "CALL", "ticker": "O:SPY250501C00320000", "expiry": "2025-05-01"}, {"strike": 325, "type": "CALL", "ticker": "O:SPY250501C00325000", "expiry": "2025-05-01"}, {"strike": 330, "type": "CALL", "ticker": "O:SPY250501C00330000", "expiry": "2025-05-01"}, {"strike": 335, "type": "CALL", "ticker": "O:SPY250501C00335000", "expiry": "2025-05-01"}, {"strike": 340, "type": "CALL", "ticker": "O:SPY250501C00340000", "expiry": "2025-05-01"}, {"strike": 345, "type": "CALL", "ticker": "O:SPY250501C00345000", "expiry": "2025-05-01"}, {"strike": 350, "type": "CALL", "ticker": "O:SPY250501C00350000", "expiry": "2025-05-01"}, {"strike": 355, "type": "CALL", "ticker": "O:SPY250501C00355000", "expiry": "2025-05-01"}, {"strike": 360, "type": "CALL", "ticker": "O:SPY250501C00360000", "expiry": "2025-05-01"}, {"strike": 365, "type": "CALL", "ticker": "O:SPY250501C00365000", "expiry": "2025-05-01"}, {"strike": 370, "type": "CALL", "ticker": "O:SPY250501C00370000", "expiry": "2025-05-01"}, {"strike": 375, "type": "CALL", "ticker": "O:SPY250501C00375000", "expiry": "2025-05-01"}, {"strike": 380, "type": "CALL", "ticker": "O:SPY250501C00380000", "expiry": "2025-05-01"}, {"strike": 385, "type": "CALL", "ticker": "O:SPY250501C00385000", "expiry": "2025-05-01"}, {"strike": 390, "type": "CALL", "ticker": "O:SPY250501C00390000", "expiry": "2025-05-01"}, {"strike": 395, "type": "CALL", "ticker": "O:SPY250501C00395000", "expiry": "2025-05-01"}, {"strike": 400, "type": "CALL", "ticker": "O:SPY250501C00400000", "expiry": "2025-05-01"}, {"strike": 405, "type": "CALL", "ticker": "O:SPY250501C00405000", "expiry": "2025-05-01"}, {"strike": 410, "type": "CALL", "ticker": "O:SPY250501C00410000", "expiry": "2025-05-01"}, {"strike": 415, "type": "CALL", "ticker": "O:SPY250501C00415000", "expiry": "2025-05-01"}, {"strike": 420, "type": "CALL", "ticker": "O:SPY250501C00420000", "expiry": "2025-05-01"}, {"strike": 425, "type": "CALL", "ticker": "O:SPY250501C00425000", "expiry": "2025-05-01"}, {"strike": 430, "type": "CALL", "ticker": "O:SPY250501C00430000", "expiry": "2025-05-01"}, {"strike": 435, "type": "CALL", "ticker": "O:SPY250501C00435000", "expiry": "2025-05-01"}, {"strike": 440, "type": "CALL", "ticker": "O:SPY250501C00440000", "expiry": "2025-05-01"}, {"strike": 441, "type": "CALL", "ticker": "O:SPY250501C00441000", "expiry": "2025-05-01"}, {"strike": 442, "type": "CALL", "ticker": "O:SPY250501C00442000", "expiry": "2025-05-01"}, {"strike": 443, "type": "CALL", "ticker": "O:SPY250501C00443000", "expiry": "2025-05-01"}, {"strike": 444, "type": "CALL", "ticker": "O:SPY250501C00444000", "expiry": "2025-05-01"}, {"strike": 445, "type": "CALL", "ticker": "O:SPY250501C00445000", "expiry": "2025-05-01"}, {"strike": 446, "type": "CALL", "ticker": "O:SPY250501C00446000", "expiry": "2025-05-01"}, {"strike": 447, "type": "CALL", "ticker": "O:SPY250501C00447000", "expiry": "2025-05-01"}, {"strike": 448, "type": "CALL", "ticker": "O:SPY250501C00448000", "expiry": "2025-05-01"}, {"strike": 449, "type": "CALL", "ticker": "O:SPY250501C00449000", "expiry": "2025-05-01"}, {"strike": 450, "type": "CALL", "ticker": "O:SPY250501C00450000", "expiry": "2025-05-01"}, {"strike": 451, "type": "CALL", "ticker": "O:SPY250501C00451000", "expiry": "2025-05-01"}, {"strike": 452, "type": "CALL", "ticker": "O:SPY250501C00452000", "expiry": "2025-05-01"}, {"strike": 453, "type": "CALL", "ticker": "O:SPY250501C00453000", "expiry": "2025-05-01"}, {"strike": 454, "type": "CALL", "ticker": "O:SPY250501C00454000", "expiry": "2025-05-01"}, {"strike": 455, "type": "CALL", "ticker": "O:SPY250501C00455000", "expiry": "2025-05-01"}, {"strike": 456, "type": "CALL", "ticker": "O:SPY250501C00456000", "expiry": "2025-05-01"}, {"strike": 457, "type": "CALL", "ticker": "O:SPY250501C00457000", "expiry": "2025-05-01"}, {"strike": 458, "type": "CALL", "ticker": "O:SPY250501C00458000", "expiry": "2025-05-01"}, {"strike": 459, "type": "CALL", "ticker": "O:SPY250501C00459000", "expiry": "2025-05-01"}, {"strike": 460, "type": "CALL", "ticker": "O:SPY250501C00460000", "expiry": "2025-05-01"}, {"strike": 461, "type": "CALL", "ticker": "O:SPY250501C00461000", "expiry": "2025-05-01"}, {"strike": 462, "type": "CALL", "ticker": "O:SPY250501C00462000", "expiry": "2025-05-01"}, {"strike": 463, "type": "CALL", "ticker": "O:SPY250501C00463000", "expiry": "2025-05-01"}, {"strike": 464, "type": "CALL", "ticker": "O:SPY250501C00464000", "expiry": "2025-05-01"}, {"strike": 465, "type": "CALL", "ticker": "O:SPY250501C00465000", "expiry": "2025-05-01"}, {"strike": 466, "type": "CALL", "ticker": "O:SPY250501C00466000", "expiry": "2025-05-01"}, {"strike": 467, "type": "CALL", "ticker": "O:SPY250501C00467000", "expiry": "2025-05-01"}, {"strike": 468, "type": "CALL", "ticker": "O:SPY250501C00468000", "expiry": "2025-05-01"}, {"strike": 469, "type": "CALL", "ticker": "O:SPY250501C00469000", "expiry": "2025-05-01"}, {"strike": 470, "type": "CALL", "ticker": "O:SPY250501C00470000", "expiry": "2025-05-01"}, {"strike": 471, "type": "CALL", "ticker": "O:SPY250501C00471000", "expiry": "2025-05-01"}, {"strike": 472, "type": "CALL", "ticker": "O:SPY250501C00472000", "expiry": "2025-05-01"}, {"strike": 473, "type": "CALL", "ticker": "O:SPY250501C00473000", "expiry": "2025-05-01"}, {"strike": 474, "type": "CALL", "ticker": "O:SPY250501C00474000", "expiry": "2025-05-01"}, {"strike": 475, "type": "CALL", "ticker": "O:SPY250501C00475000", "expiry": "2025-05-01"}, {"strike": 476, "type": "CALL", "ticker": "O:SPY250501C00476000", "expiry": "2025-05-01"}, {"strike": 477, "type": "CALL", "ticker": "O:SPY250501C00477000", "expiry": "2025-05-01"}, {"strike": 478, "type": "CALL", "ticker": "O:SPY250501C00478000", "expiry": "2025-05-01"}, {"strike": 479, "type": "CALL", "ticker": "O:SPY250501C00479000", "expiry": "2025-05-01"}, {"strike": 480, "type": "CALL", "ticker": "O:SPY250501C00480000", "expiry": "2025-05-01"}, {"strike": 481, "type": "CALL", "ticker": "O:SPY250501C00481000", "expiry": "2025-05-01"}, {"strike": 482, "type": "CALL", "ticker": "O:SPY250501C00482000", "expiry": "2025-05-01"}, {"strike": 483, "type": "CALL", "ticker": "O:SPY250501C00483000", "expiry": "2025-05-01"}, {"strike": 484, "type": "CALL", "ticker": "O:SPY250501C00484000", "expiry": "2025-05-01"}, {"strike": 485, "type": "CALL", "ticker": "O:SPY250501C00485000", "expiry": "2025-05-01"}, {"strike": 486, "type": "CALL", "ticker": "O:SPY250501C00486000", "expiry": "2025-05-01"}, {"strike": 487, "type": "CALL", "ticker": "O:SPY250501C00487000", "expiry": "2025-05-01"}, {"strike": 488, "type": "CALL", "ticker": "O:SPY250501C00488000", "expiry": "2025-05-01"}, {"strike": 489, "type": "CALL", "ticker": "O:SPY250501C00489000", "expiry": "2025-05-01"}, {"strike": 490, "type": "CALL", "ticker": "O:SPY250501C00490000", "expiry": "2025-05-01"}, {"strike": 491, "type": "CALL", "ticker": "O:SPY250501C00491000", "expiry": "2025-05-01"}, {"strike": 492, "type": "CALL", "ticker": "O:SPY250501C00492000", "expiry": "2025-05-01"}, {"strike": 493, "type": "CALL", "ticker": "O:SPY250501C00493000", "expiry": "2025-05-01"}, {"strike": 494, "type": "CALL", "ticker": "O:SPY250501C00494000", "expiry": "2025-05-01"}, {"strike": 495, "type": "CALL", "ticker": "O:SPY250501C00495000", "expiry": "2025-05-01"}, {"strike": 496, "type": "CALL", "ticker": "O:SPY250501C00496000", "expiry": "2025-05-01"}, {"strike": 497, "type": "CALL", "ticker": "O:SPY250501C00497000", "expiry": "2025-05-01"}, {"strike": 498, "type": "CALL", "ticker": "O:SPY250501C00498000", "expiry": "2025-05-01"}, {"strike": 499, "type": "CALL", "ticker": "O:SPY250501C00499000", "expiry": "2025-05-01"}, {"strike": 500, "type": "CALL", "ticker": "O:SPY250501C00500000", "expiry": "2025-05-01"}, {"strike": 501, "type": "CALL", "ticker": "O:SPY250501C00501000", "expiry": "2025-05-01"}, {"strike": 502, "type": "CALL", "ticker": "O:SPY250501C00502000", "expiry": "2025-05-01"}, {"strike": 503, "type": "CALL", "ticker": "O:SPY250501C00503000", "expiry": "2025-05-01"}, {"strike": 504, "type": "CALL", "ticker": "O:SPY250501C00504000", "expiry": "2025-05-01"}, {"strike": 505, "type": "CALL", "ticker": "O:SPY250501C00505000", "expiry": "2025-05-01"}, {"strike": 506, "type": "CALL", "ticker": "O:SPY250501C00506000", "expiry": "2025-05-01"}, {"strike": 507, "type": "CALL", "ticker": "O:SPY250501C00507000", "expiry": "2025-05-01"}, {"strike": 508, "type": "CALL", "ticker": "O:SPY250501C00508000", "expiry": "2025-05-01"}, {"strike": 509, "type": "CALL", "ticker": "O:SPY250501C00509000", "expiry": "2025-05-01"}, {"strike": 510, "type": "CALL", "ticker": "O:SPY250501C00510000", "expiry": "2025-05-01"}, {"strike": 511, "type": "CALL", "ticker": "O:SPY250501C00511000", "expiry": "2025-05-01"}, {"strike": 512, "type": "CALL", "ticker": "O:SPY250501C00512000", "expiry": "2025-05-01"}, {"strike": 513, "type": "CALL", "ticker": "O:SPY250501C00513000", "expiry": "2025-05-01"}, {"strike": 514, "type": "CALL", "ticker": "O:SPY250501C00514000", "expiry": "2025-05-01"}, {"strike": 515, "type": "CALL", "ticker": "O:SPY250501C00515000", "expiry": "2025-05-01"}, {"strike": 516, "type": "CALL", "ticker": "O:SPY250501C00516000", "expiry": "2025-05-01"}, {"strike": 517, "type": "CALL", "ticker": "O:SPY250501C00517000", "expiry": "2025-05-01"}, {"strike": 518, "type": "CALL", "ticker": "O:SPY250501C00518000", "expiry": "2025-05-01"}, {"strike": 519, "type": "CALL", "ticker": "O:SPY250501C00519000", "expiry": "2025-05-01"}, {"strike": 520, "type": "CALL", "ticker": "O:SPY250501C00520000", "expiry": "2025-05-01"}, {"strike": 521, "type": "CALL", "ticker": "O:SPY250501C00521000", "expiry": "2025-05-01"}, {"strike": 522, "type": "CALL", "ticker": "O:SPY250501C00522000", "expiry": "2025-05-01"}, {"strike": 523, "type": "CALL", "ticker": "O:SPY250501C00523000", "expiry": "2025-05-01"}, {"strike": 524, "type": "CALL", "ticker": "O:SPY250501C00524000", "expiry": "2025-05-01"}, {"strike": 525, "type": "CALL", "ticker": "O:SPY250501C00525000", "expiry": "2025-05-01"}, {"strike": 526, "type": "CALL", "ticker": "O:SPY250501C00526000", "expiry": "2025-05-01"}, {"strike": 527, "type": "CALL", "ticker": "O:SPY250501C00527000", "expiry": "2025-05-01"}, {"strike": 528, "type": "CALL", "ticker": "O:SPY250501C00528000", "expiry": "2025-05-01"}, {"strike": 529, "type": "CALL", "ticker": "O:SPY250501C00529000", "expiry": "2025-05-01"}, {"strike": 530, "type": "CALL", "ticker": "O:SPY250501C00530000", "expiry": "2025-05-01"}, {"strike": 531, "type": "CALL", "ticker": "O:SPY250501C00531000", "expiry": "2025-05-01"}, {"strike": 532, "type": "CALL", "ticker": "O:SPY250501C00532000", "expiry": "2025-05-01"}, {"strike": 533, "type": "CALL", "ticker": "O:SPY250501C00533000", "expiry": "2025-05-01"}, {"strike": 534, "type": "CALL", "ticker": "O:SPY250501C00534000", "expiry": "2025-05-01"}, {"strike": 535, "type": "CALL", "ticker": "O:SPY250501C00535000", "expiry": "2025-05-01"}, {"strike": 536, "type": "CALL", "ticker": "O:SPY250501C00536000", "expiry": "2025-05-01"}, {"strike": 537, "type": "CALL", "ticker": "O:SPY250501C00537000", "expiry": "2025-05-01"}, {"strike": 538, "type": "CALL", "ticker": "O:SPY250501C00538000", "expiry": "2025-05-01"}, {"strike": 539, "type": "CALL", "ticker": "O:SPY250501C00539000", "expiry": "2025-05-01"}, {"strike": 540, "type": "CALL", "ticker": "O:SPY250501C00540000", "expiry": "2025-05-01"}, {"strike": 541, "type": "CALL", "ticker": "O:SPY250501C00541000", "expiry": "2025-05-01"}, {"strike": 542, "type": "CALL", "ticker": "O:SPY250501C00542000", "expiry": "2025-05-01"}, {"strike": 543, "type": "CALL", "ticker": "O:SPY250501C00543000", "expiry": "2025-05-01"}, {"strike": 544, "type": "CALL", "ticker": "O:SPY250501C00544000", "expiry": "2025-05-01"}, {"strike": 545, "type": "CALL", "ticker": "O:SPY250501C00545000", "expiry": "2025-05-01"}, {"strike": 546, "type": "CALL", "ticker": "O:SPY250501C00546000", "expiry": "2025-05-01"}, {"strike": 547, "type": "CALL", "ticker": "O:SPY250501C00547000", "expiry": "2025-05-01"}, {"strike": 548, "type": "CALL", "ticker": "O:SPY250501C00548000", "expiry": "2025-05-01"}, {"strike": 549, "type": "CALL", "ticker": "O:SPY250501C00549000", "expiry": "2025-05-01"}, {"strike": 550, "type": "CALL", "ticker": "O:SPY250501C00550000", "expiry": "2025-05-01"}, {"strike": 551, "type": "CALL", "ticker": "O:SPY250501C00551000", "expiry": "2025-05-01"}, {"strike": 552, "type": "CALL", "ticker": "O:SPY250501C00552000", "expiry": "2025-05-01"}, {"strike": 553, "type": "CALL", "ticker": "O:SPY250501C00553000", "expiry": "2025-05-01"}, {"strike": 554, "type": "CALL", "ticker": "O:SPY250501C00554000", "expiry": "2025-05-01"}, {"strike": 555, "type": "CALL", "ticker": "O:SPY250501C00555000", "expiry": "2025-05-01"}, {"strike": 556, "type": "CALL", "ticker": "O:SPY250501C00556000", "expiry": "2025-05-01"}, {"strike": 557, "type": "CALL", "ticker": "O:SPY250501C00557000", "expiry": "2025-05-01"}, {"strike": 558, "type": "CALL", "ticker": "O:SPY250501C00558000", "expiry": "2025-05-01"}, {"strike": 559, "type": "CALL", "ticker": "O:SPY250501C00559000", "expiry": "2025-05-01"}, {"strike": 560, "type": "CALL", "ticker": "O:SPY250501C00560000", "expiry": "2025-05-01"}, {"strike": 561, "type": "CALL", "ticker": "O:SPY250501C00561000", "expiry": "2025-05-01"}, {"strike": 562, "type": "CALL", "ticker": "O:SPY250501C00562000", "expiry": "2025-05-01"}, {"strike": 563, "type": "CALL", "ticker": "O:SPY250501C00563000", "expiry": "2025-05-01"}, {"strike": 564, "type": "CALL", "ticker": "O:SPY250501C00564000", "expiry": "2025-05-01"}, {"strike": 565, "type": "CALL", "ticker": "O:SPY250501C00565000", "expiry": "2025-05-01"}, {"strike": 566, "type": "CALL", "ticker": "O:SPY250501C00566000", "expiry": "2025-05-01"}, {"strike": 567, "type": "CALL", "ticker": "O:SPY250501C00567000", "expiry": "2025-05-01"}, {"strike": 568, "type": "CALL", "ticker": "O:SPY250501C00568000", "expiry": "2025-05-01"}, {"strike": 569, "type": "CALL", "ticker": "O:SPY250501C00569000", "expiry": "2025-05-01"}, {"strike": 570, "type": "CALL", "ticker": "O:SPY250501C00570000", "expiry": "2025-05-01"}, {"strike": 571, "type": "CALL", "ticker": "O:SPY250501C00571000", "expiry": "2025-05-01"}, {"strike": 572, "type": "CALL", "ticker": "O:SPY250501C00572000", "expiry": "2025-05-01"}, {"strike": 573, "type": "CALL", "ticker": "O:SPY250501C00573000", "expiry": "2025-05-01"}, {"strike": 574, "type": "CALL", "ticker": "O:SPY250501C00574000", "expiry": "2025-05-01"}, {"strike": 575, "type": "CALL", "ticker": "O:SPY250501C00575000", "expiry": "2025-05-01"}, {"strike": 576, "type": "CALL", "ticker": "O:SPY250501C00576000", "expiry": "2025-05-01"}, {"strike": 577, "type": "CALL", "ticker": "O:SPY250501C00577000", "expiry": "2025-05-01"}, {"strike": 578, "type": "CALL", "ticker": "O:SPY250501C00578000", "expiry": "2025-05-01"}, {"strike": 579, "type": "CALL", "ticker": "O:SPY250501C00579000", "expiry": "2025-05-01"}, {"strike": 580, "type": "CALL", "ticker": "O:SPY250501C00580000", "expiry": "2025-05-01"}, {"strike": 585, "type": "CALL", "ticker": "O:SPY250501C00585000", "expiry": "2025-05-01"}, {"strike": 590, "type": "CALL", "ticker": "O:SPY250501C00590000", "expiry": "2025-05-01"}, {"strike": 595, "type": "CALL", "ticker": "O:SPY250501C00595000", "expiry": "2025-05-01"}, {"strike": 600, "type": "CALL", "ticker": "O:SPY250501C00600000", "expiry": "2025-05-01"}, {"strike": 605, "type": "CALL", "ticker": "O:SPY250501C00605000", "expiry": "2025-05-01"}, {"strike": 610, "type": "CALL", "ticker": "O:SPY250501C00610000", "expiry": "2025-05-01"}, {"strike": 615, "type": "CALL", "ticker": "O:SPY250501C00615000", "expiry": "2025-05-01"}, {"strike": 620, "type": "CALL", "ticker": "O:SPY250501C00620000", "expiry": "2025-05-01"}, {"strike": 625, "type": "CALL", "ticker": "O:SPY250501C00625000", "expiry": "2025-05-01"}, {"strike": 630, "type": "CALL", "ticker": "O:SPY250501C00630000", "expiry": "2025-05-01"}, {"strike": 635, "type": "CALL", "ticker": "O:SPY250501C00635000", "expiry": "2025-05-01"}, {"strike": 640, "type": "CALL", "ticker": "O:SPY250501C00640000", "expiry": "2025-05-01"}, {"strike": 645, "type": "CALL", "ticker": "O:SPY250501C00645000", "expiry": "2025-05-01"}, {"strike": 650, "type": "CALL", "ticker": "O:SPY250501C00650000", "expiry": "2025-05-01"}]