[{"strike": 370, "type": "CALL", "ticker": "O:SPY231019C00370000", "expiry": "2023-10-19"}, {"strike": 371, "type": "CALL", "ticker": "O:SPY231019C00371000", "expiry": "2023-10-19"}, {"strike": 372, "type": "CALL", "ticker": "O:SPY231019C00372000", "expiry": "2023-10-19"}, {"strike": 373, "type": "CALL", "ticker": "O:SPY231019C00373000", "expiry": "2023-10-19"}, {"strike": 374, "type": "CALL", "ticker": "O:SPY231019C00374000", "expiry": "2023-10-19"}, {"strike": 375, "type": "CALL", "ticker": "O:SPY231019C00375000", "expiry": "2023-10-19"}, {"strike": 376, "type": "CALL", "ticker": "O:SPY231019C00376000", "expiry": "2023-10-19"}, {"strike": 377, "type": "CALL", "ticker": "O:SPY231019C00377000", "expiry": "2023-10-19"}, {"strike": 378, "type": "CALL", "ticker": "O:SPY231019C00378000", "expiry": "2023-10-19"}, {"strike": 379, "type": "CALL", "ticker": "O:SPY231019C00379000", "expiry": "2023-10-19"}, {"strike": 380, "type": "CALL", "ticker": "O:SPY231019C00380000", "expiry": "2023-10-19"}, {"strike": 381, "type": "CALL", "ticker": "O:SPY231019C00381000", "expiry": "2023-10-19"}, {"strike": 382, "type": "CALL", "ticker": "O:SPY231019C00382000", "expiry": "2023-10-19"}, {"strike": 383, "type": "CALL", "ticker": "O:SPY231019C00383000", "expiry": "2023-10-19"}, {"strike": 384, "type": "CALL", "ticker": "O:SPY231019C00384000", "expiry": "2023-10-19"}, {"strike": 385, "type": "CALL", "ticker": "O:SPY231019C00385000", "expiry": "2023-10-19"}, {"strike": 386, "type": "CALL", "ticker": "O:SPY231019C00386000", "expiry": "2023-10-19"}, {"strike": 387, "type": "CALL", "ticker": "O:SPY231019C00387000", "expiry": "2023-10-19"}, {"strike": 388, "type": "CALL", "ticker": "O:SPY231019C00388000", "expiry": "2023-10-19"}, {"strike": 389, "type": "CALL", "ticker": "O:SPY231019C00389000", "expiry": "2023-10-19"}, {"strike": 390, "type": "CALL", "ticker": "O:SPY231019C00390000", "expiry": "2023-10-19"}, {"strike": 391, "type": "CALL", "ticker": "O:SPY231019C00391000", "expiry": "2023-10-19"}, {"strike": 392, "type": "CALL", "ticker": "O:SPY231019C00392000", "expiry": "2023-10-19"}, {"strike": 393, "type": "CALL", "ticker": "O:SPY231019C00393000", "expiry": "2023-10-19"}, {"strike": 394, "type": "CALL", "ticker": "O:SPY231019C00394000", "expiry": "2023-10-19"}, {"strike": 395, "type": "CALL", "ticker": "O:SPY231019C00395000", "expiry": "2023-10-19"}, {"strike": 396, "type": "CALL", "ticker": "O:SPY231019C00396000", "expiry": "2023-10-19"}, {"strike": 397, "type": "CALL", "ticker": "O:SPY231019C00397000", "expiry": "2023-10-19"}, {"strike": 398, "type": "CALL", "ticker": "O:SPY231019C00398000", "expiry": "2023-10-19"}, {"strike": 399, "type": "CALL", "ticker": "O:SPY231019C00399000", "expiry": "2023-10-19"}, {"strike": 400, "type": "CALL", "ticker": "O:SPY231019C00400000", "expiry": "2023-10-19"}, {"strike": 401, "type": "CALL", "ticker": "O:SPY231019C00401000", "expiry": "2023-10-19"}, {"strike": 402, "type": "CALL", "ticker": "O:SPY231019C00402000", "expiry": "2023-10-19"}, {"strike": 403, "type": "CALL", "ticker": "O:SPY231019C00403000", "expiry": "2023-10-19"}, {"strike": 404, "type": "CALL", "ticker": "O:SPY231019C00404000", "expiry": "2023-10-19"}, {"strike": 405, "type": "CALL", "ticker": "O:SPY231019C00405000", "expiry": "2023-10-19"}, {"strike": 406, "type": "CALL", "ticker": "O:SPY231019C00406000", "expiry": "2023-10-19"}, {"strike": 407, "type": "CALL", "ticker": "O:SPY231019C00407000", "expiry": "2023-10-19"}, {"strike": 408, "type": "CALL", "ticker": "O:SPY231019C00408000", "expiry": "2023-10-19"}, {"strike": 409, "type": "CALL", "ticker": "O:SPY231019C00409000", "expiry": "2023-10-19"}, {"strike": 410, "type": "CALL", "ticker": "O:SPY231019C00410000", "expiry": "2023-10-19"}, {"strike": 411, "type": "CALL", "ticker": "O:SPY231019C00411000", "expiry": "2023-10-19"}, {"strike": 412, "type": "CALL", "ticker": "O:SPY231019C00412000", "expiry": "2023-10-19"}, {"strike": 413, "type": "CALL", "ticker": "O:SPY231019C00413000", "expiry": "2023-10-19"}, {"strike": 414, "type": "CALL", "ticker": "O:SPY231019C00414000", "expiry": "2023-10-19"}, {"strike": 415, "type": "CALL", "ticker": "O:SPY231019C00415000", "expiry": "2023-10-19"}, {"strike": 416, "type": "CALL", "ticker": "O:SPY231019C00416000", "expiry": "2023-10-19"}, {"strike": 417, "type": "CALL", "ticker": "O:SPY231019C00417000", "expiry": "2023-10-19"}, {"strike": 418, "type": "CALL", "ticker": "O:SPY231019C00418000", "expiry": "2023-10-19"}, {"strike": 419, "type": "CALL", "ticker": "O:SPY231019C00419000", "expiry": "2023-10-19"}, {"strike": 420, "type": "CALL", "ticker": "O:SPY231019C00420000", "expiry": "2023-10-19"}, {"strike": 421, "type": "CALL", "ticker": "O:SPY231019C00421000", "expiry": "2023-10-19"}, {"strike": 422, "type": "CALL", "ticker": "O:SPY231019C00422000", "expiry": "2023-10-19"}, {"strike": 423, "type": "CALL", "ticker": "O:SPY231019C00423000", "expiry": "2023-10-19"}, {"strike": 424, "type": "CALL", "ticker": "O:SPY231019C00424000", "expiry": "2023-10-19"}, {"strike": 425, "type": "CALL", "ticker": "O:SPY231019C00425000", "expiry": "2023-10-19"}, {"strike": 426, "type": "CALL", "ticker": "O:SPY231019C00426000", "expiry": "2023-10-19"}, {"strike": 427, "type": "CALL", "ticker": "O:SPY231019C00427000", "expiry": "2023-10-19"}, {"strike": 428, "type": "CALL", "ticker": "O:SPY231019C00428000", "expiry": "2023-10-19"}, {"strike": 429, "type": "CALL", "ticker": "O:SPY231019C00429000", "expiry": "2023-10-19"}, {"strike": 430, "type": "CALL", "ticker": "O:SPY231019C00430000", "expiry": "2023-10-19"}, {"strike": 431, "type": "CALL", "ticker": "O:SPY231019C00431000", "expiry": "2023-10-19"}, {"strike": 432, "type": "CALL", "ticker": "O:SPY231019C00432000", "expiry": "2023-10-19"}, {"strike": 433, "type": "CALL", "ticker": "O:SPY231019C00433000", "expiry": "2023-10-19"}, {"strike": 434, "type": "CALL", "ticker": "O:SPY231019C00434000", "expiry": "2023-10-19"}, {"strike": 435, "type": "CALL", "ticker": "O:SPY231019C00435000", "expiry": "2023-10-19"}, {"strike": 436, "type": "CALL", "ticker": "O:SPY231019C00436000", "expiry": "2023-10-19"}, {"strike": 437, "type": "CALL", "ticker": "O:SPY231019C00437000", "expiry": "2023-10-19"}, {"strike": 438, "type": "CALL", "ticker": "O:SPY231019C00438000", "expiry": "2023-10-19"}, {"strike": 439, "type": "CALL", "ticker": "O:SPY231019C00439000", "expiry": "2023-10-19"}, {"strike": 440, "type": "CALL", "ticker": "O:SPY231019C00440000", "expiry": "2023-10-19"}, {"strike": 441, "type": "CALL", "ticker": "O:SPY231019C00441000", "expiry": "2023-10-19"}, {"strike": 442, "type": "CALL", "ticker": "O:SPY231019C00442000", "expiry": "2023-10-19"}, {"strike": 443, "type": "CALL", "ticker": "O:SPY231019C00443000", "expiry": "2023-10-19"}, {"strike": 444, "type": "CALL", "ticker": "O:SPY231019C00444000", "expiry": "2023-10-19"}, {"strike": 445, "type": "CALL", "ticker": "O:SPY231019C00445000", "expiry": "2023-10-19"}, {"strike": 446, "type": "CALL", "ticker": "O:SPY231019C00446000", "expiry": "2023-10-19"}, {"strike": 447, "type": "CALL", "ticker": "O:SPY231019C00447000", "expiry": "2023-10-19"}, {"strike": 448, "type": "CALL", "ticker": "O:SPY231019C00448000", "expiry": "2023-10-19"}, {"strike": 449, "type": "CALL", "ticker": "O:SPY231019C00449000", "expiry": "2023-10-19"}, {"strike": 450, "type": "CALL", "ticker": "O:SPY231019C00450000", "expiry": "2023-10-19"}, {"strike": 451, "type": "CALL", "ticker": "O:SPY231019C00451000", "expiry": "2023-10-19"}, {"strike": 452, "type": "CALL", "ticker": "O:SPY231019C00452000", "expiry": "2023-10-19"}, {"strike": 453, "type": "CALL", "ticker": "O:SPY231019C00453000", "expiry": "2023-10-19"}, {"strike": 454, "type": "CALL", "ticker": "O:SPY231019C00454000", "expiry": "2023-10-19"}, {"strike": 455, "type": "CALL", "ticker": "O:SPY231019C00455000", "expiry": "2023-10-19"}, {"strike": 456, "type": "CALL", "ticker": "O:SPY231019C00456000", "expiry": "2023-10-19"}, {"strike": 457, "type": "CALL", "ticker": "O:SPY231019C00457000", "expiry": "2023-10-19"}, {"strike": 458, "type": "CALL", "ticker": "O:SPY231019C00458000", "expiry": "2023-10-19"}, {"strike": 459, "type": "CALL", "ticker": "O:SPY231019C00459000", "expiry": "2023-10-19"}, {"strike": 460, "type": "CALL", "ticker": "O:SPY231019C00460000", "expiry": "2023-10-19"}, {"strike": 461, "type": "CALL", "ticker": "O:SPY231019C00461000", "expiry": "2023-10-19"}, {"strike": 462, "type": "CALL", "ticker": "O:SPY231019C00462000", "expiry": "2023-10-19"}, {"strike": 463, "type": "CALL", "ticker": "O:SPY231019C00463000", "expiry": "2023-10-19"}, {"strike": 464, "type": "CALL", "ticker": "O:SPY231019C00464000", "expiry": "2023-10-19"}, {"strike": 465, "type": "CALL", "ticker": "O:SPY231019C00465000", "expiry": "2023-10-19"}, {"strike": 466, "type": "CALL", "ticker": "O:SPY231019C00466000", "expiry": "2023-10-19"}, {"strike": 467, "type": "CALL", "ticker": "O:SPY231019C00467000", "expiry": "2023-10-19"}, {"strike": 468, "type": "CALL", "ticker": "O:SPY231019C00468000", "expiry": "2023-10-19"}, {"strike": 469, "type": "CALL", "ticker": "O:SPY231019C00469000", "expiry": "2023-10-19"}, {"strike": 470, "type": "CALL", "ticker": "O:SPY231019C00470000", "expiry": "2023-10-19"}, {"strike": 471, "type": "CALL", "ticker": "O:SPY231019C00471000", "expiry": "2023-10-19"}, {"strike": 472, "type": "CALL", "ticker": "O:SPY231019C00472000", "expiry": "2023-10-19"}, {"strike": 473, "type": "CALL", "ticker": "O:SPY231019C00473000", "expiry": "2023-10-19"}, {"strike": 474, "type": "CALL", "ticker": "O:SPY231019C00474000", "expiry": "2023-10-19"}, {"strike": 475, "type": "CALL", "ticker": "O:SPY231019C00475000", "expiry": "2023-10-19"}, {"strike": 476, "type": "CALL", "ticker": "O:SPY231019C00476000", "expiry": "2023-10-19"}, {"strike": 477, "type": "CALL", "ticker": "O:SPY231019C00477000", "expiry": "2023-10-19"}, {"strike": 478, "type": "CALL", "ticker": "O:SPY231019C00478000", "expiry": "2023-10-19"}, {"strike": 479, "type": "CALL", "ticker": "O:SPY231019C00479000", "expiry": "2023-10-19"}, {"strike": 480, "type": "CALL", "ticker": "O:SPY231019C00480000", "expiry": "2023-10-19"}, {"strike": 481, "type": "CALL", "ticker": "O:SPY231019C00481000", "expiry": "2023-10-19"}, {"strike": 482, "type": "CALL", "ticker": "O:SPY231019C00482000", "expiry": "2023-10-19"}, {"strike": 483, "type": "CALL", "ticker": "O:SPY231019C00483000", "expiry": "2023-10-19"}, {"strike": 484, "type": "CALL", "ticker": "O:SPY231019C00484000", "expiry": "2023-10-19"}, {"strike": 485, "type": "CALL", "ticker": "O:SPY231019C00485000", "expiry": "2023-10-19"}, {"strike": 486, "type": "CALL", "ticker": "O:SPY231019C00486000", "expiry": "2023-10-19"}, {"strike": 487, "type": "CALL", "ticker": "O:SPY231019C00487000", "expiry": "2023-10-19"}, {"strike": 488, "type": "CALL", "ticker": "O:SPY231019C00488000", "expiry": "2023-10-19"}, {"strike": 489, "type": "CALL", "ticker": "O:SPY231019C00489000", "expiry": "2023-10-19"}, {"strike": 490, "type": "CALL", "ticker": "O:SPY231019C00490000", "expiry": "2023-10-19"}, {"strike": 491, "type": "CALL", "ticker": "O:SPY231019C00491000", "expiry": "2023-10-19"}, {"strike": 492, "type": "CALL", "ticker": "O:SPY231019C00492000", "expiry": "2023-10-19"}, {"strike": 493, "type": "CALL", "ticker": "O:SPY231019C00493000", "expiry": "2023-10-19"}, {"strike": 494, "type": "CALL", "ticker": "O:SPY231019C00494000", "expiry": "2023-10-19"}, {"strike": 495, "type": "CALL", "ticker": "O:SPY231019C00495000", "expiry": "2023-10-19"}, {"strike": 496, "type": "CALL", "ticker": "O:SPY231019C00496000", "expiry": "2023-10-19"}, {"strike": 497, "type": "CALL", "ticker": "O:SPY231019C00497000", "expiry": "2023-10-19"}, {"strike": 498, "type": "CALL", "ticker": "O:SPY231019C00498000", "expiry": "2023-10-19"}, {"strike": 499, "type": "CALL", "ticker": "O:SPY231019C00499000", "expiry": "2023-10-19"}, {"strike": 500, "type": "CALL", "ticker": "O:SPY231019C00500000", "expiry": "2023-10-19"}]