[{"strike": 155, "type": "PUT", "ticker": "O:QQQ210122P00155000", "expiry": "2021-01-22"}, {"strike": 160, "type": "PUT", "ticker": "O:QQQ210122P00160000", "expiry": "2021-01-22"}, {"strike": 165, "type": "PUT", "ticker": "O:QQQ210122P00165000", "expiry": "2021-01-22"}, {"strike": 170, "type": "PUT", "ticker": "O:QQQ210122P00170000", "expiry": "2021-01-22"}, {"strike": 175, "type": "PUT", "ticker": "O:QQQ210122P00175000", "expiry": "2021-01-22"}, {"strike": 180, "type": "PUT", "ticker": "O:QQQ210122P00180000", "expiry": "2021-01-22"}, {"strike": 185, "type": "PUT", "ticker": "O:QQQ210122P00185000", "expiry": "2021-01-22"}, {"strike": 190, "type": "PUT", "ticker": "O:QQQ210122P00190000", "expiry": "2021-01-22"}, {"strike": 195, "type": "PUT", "ticker": "O:QQQ210122P00195000", "expiry": "2021-01-22"}, {"strike": 200, "type": "PUT", "ticker": "O:QQQ210122P00200000", "expiry": "2021-01-22"}, {"strike": 205, "type": "PUT", "ticker": "O:QQQ210122P00205000", "expiry": "2021-01-22"}, {"strike": 210, "type": "PUT", "ticker": "O:QQQ210122P00210000", "expiry": "2021-01-22"}, {"strike": 214, "type": "PUT", "ticker": "O:QQQ210122P00214000", "expiry": "2021-01-22"}, {"strike": 215, "type": "PUT", "ticker": "O:QQQ210122P00215000", "expiry": "2021-01-22"}, {"strike": 220, "type": "PUT", "ticker": "O:QQQ210122P00220000", "expiry": "2021-01-22"}, {"strike": 225, "type": "PUT", "ticker": "O:QQQ210122P00225000", "expiry": "2021-01-22"}, {"strike": 230, "type": "PUT", "ticker": "O:QQQ210122P00230000", "expiry": "2021-01-22"}, {"strike": 235, "type": "PUT", "ticker": "O:QQQ210122P00235000", "expiry": "2021-01-22"}, {"strike": 240, "type": "PUT", "ticker": "O:QQQ210122P00240000", "expiry": "2021-01-22"}, {"strike": 245, "type": "PUT", "ticker": "O:QQQ210122P00245000", "expiry": "2021-01-22"}, {"strike": 250, "type": "PUT", "ticker": "O:QQQ210122P00250000", "expiry": "2021-01-22"}, {"strike": 255, "type": "PUT", "ticker": "O:QQQ210122P00255000", "expiry": "2021-01-22"}, {"strike": 260, "type": "PUT", "ticker": "O:QQQ210122P00260000", "expiry": "2021-01-22"}, {"strike": 265, "type": "PUT", "ticker": "O:QQQ210122P00265000", "expiry": "2021-01-22"}, {"strike": 267.5, "type": "PUT", "ticker": "O:QQQ210122P00267500", "expiry": "2021-01-22"}, {"strike": 270, "type": "PUT", "ticker": "O:QQQ210122P00270000", "expiry": "2021-01-22"}, {"strike": 272.5, "type": "PUT", "ticker": "O:QQQ210122P00272500", "expiry": "2021-01-22"}, {"strike": 275, "type": "PUT", "ticker": "O:QQQ210122P00275000", "expiry": "2021-01-22"}, {"strike": 276, "type": "PUT", "ticker": "O:QQQ210122P00276000", "expiry": "2021-01-22"}, {"strike": 277.5, "type": "PUT", "ticker": "O:QQQ210122P00277500", "expiry": "2021-01-22"}, {"strike": 278, "type": "PUT", "ticker": "O:QQQ210122P00278000", "expiry": "2021-01-22"}, {"strike": 279, "type": "PUT", "ticker": "O:QQQ210122P00279000", "expiry": "2021-01-22"}, {"strike": 280, "type": "PUT", "ticker": "O:QQQ210122P00280000", "expiry": "2021-01-22"}, {"strike": 281, "type": "PUT", "ticker": "O:QQQ210122P00281000", "expiry": "2021-01-22"}, {"strike": 282, "type": "PUT", "ticker": "O:QQQ210122P00282000", "expiry": "2021-01-22"}, {"strike": 282.5, "type": "PUT", "ticker": "O:QQQ210122P00282500", "expiry": "2021-01-22"}, {"strike": 283, "type": "PUT", "ticker": "O:QQQ210122P00283000", "expiry": "2021-01-22"}, {"strike": 284, "type": "PUT", "ticker": "O:QQQ210122P00284000", "expiry": "2021-01-22"}, {"strike": 285, "type": "PUT", "ticker": "O:QQQ210122P00285000", "expiry": "2021-01-22"}, {"strike": 286, "type": "PUT", "ticker": "O:QQQ210122P00286000", "expiry": "2021-01-22"}, {"strike": 287, "type": "PUT", "ticker": "O:QQQ210122P00287000", "expiry": "2021-01-22"}, {"strike": 287.5, "type": "PUT", "ticker": "O:QQQ210122P00287500", "expiry": "2021-01-22"}, {"strike": 288, "type": "PUT", "ticker": "O:QQQ210122P00288000", "expiry": "2021-01-22"}, {"strike": 289, "type": "PUT", "ticker": "O:QQQ210122P00289000", "expiry": "2021-01-22"}, {"strike": 290, "type": "PUT", "ticker": "O:QQQ210122P00290000", "expiry": "2021-01-22"}, {"strike": 291, "type": "PUT", "ticker": "O:QQQ210122P00291000", "expiry": "2021-01-22"}, {"strike": 292, "type": "PUT", "ticker": "O:QQQ210122P00292000", "expiry": "2021-01-22"}, {"strike": 292.5, "type": "PUT", "ticker": "O:QQQ210122P00292500", "expiry": "2021-01-22"}, {"strike": 293, "type": "PUT", "ticker": "O:QQQ210122P00293000", "expiry": "2021-01-22"}, {"strike": 294, "type": "PUT", "ticker": "O:QQQ210122P00294000", "expiry": "2021-01-22"}, {"strike": 295, "type": "PUT", "ticker": "O:QQQ210122P00295000", "expiry": "2021-01-22"}, {"strike": 296, "type": "PUT", "ticker": "O:QQQ210122P00296000", "expiry": "2021-01-22"}, {"strike": 297, "type": "PUT", "ticker": "O:QQQ210122P00297000", "expiry": "2021-01-22"}, {"strike": 297.5, "type": "PUT", "ticker": "O:QQQ210122P00297500", "expiry": "2021-01-22"}, {"strike": 298, "type": "PUT", "ticker": "O:QQQ210122P00298000", "expiry": "2021-01-22"}, {"strike": 299, "type": "PUT", "ticker": "O:QQQ210122P00299000", "expiry": "2021-01-22"}, {"strike": 300, "type": "PUT", "ticker": "O:QQQ210122P00300000", "expiry": "2021-01-22"}, {"strike": 301, "type": "PUT", "ticker": "O:QQQ210122P00301000", "expiry": "2021-01-22"}, {"strike": 302, "type": "PUT", "ticker": "O:QQQ210122P00302000", "expiry": "2021-01-22"}, {"strike": 302.5, "type": "PUT", "ticker": "O:QQQ210122P00302500", "expiry": "2021-01-22"}, {"strike": 303, "type": "PUT", "ticker": "O:QQQ210122P00303000", "expiry": "2021-01-22"}, {"strike": 304, "type": "PUT", "ticker": "O:QQQ210122P00304000", "expiry": "2021-01-22"}, {"strike": 305, "type": "PUT", "ticker": "O:QQQ210122P00305000", "expiry": "2021-01-22"}, {"strike": 306, "type": "PUT", "ticker": "O:QQQ210122P00306000", "expiry": "2021-01-22"}, {"strike": 307, "type": "PUT", "ticker": "O:QQQ210122P00307000", "expiry": "2021-01-22"}, {"strike": 307.5, "type": "PUT", "ticker": "O:QQQ210122P00307500", "expiry": "2021-01-22"}, {"strike": 308, "type": "PUT", "ticker": "O:QQQ210122P00308000", "expiry": "2021-01-22"}, {"strike": 309, "type": "PUT", "ticker": "O:QQQ210122P00309000", "expiry": "2021-01-22"}, {"strike": 310, "type": "PUT", "ticker": "O:QQQ210122P00310000", "expiry": "2021-01-22"}, {"strike": 311, "type": "PUT", "ticker": "O:QQQ210122P00311000", "expiry": "2021-01-22"}, {"strike": 312, "type": "PUT", "ticker": "O:QQQ210122P00312000", "expiry": "2021-01-22"}, {"strike": 312.5, "type": "PUT", "ticker": "O:QQQ210122P00312500", "expiry": "2021-01-22"}, {"strike": 313, "type": "PUT", "ticker": "O:QQQ210122P00313000", "expiry": "2021-01-22"}, {"strike": 314, "type": "PUT", "ticker": "O:QQQ210122P00314000", "expiry": "2021-01-22"}, {"strike": 315, "type": "PUT", "ticker": "O:QQQ210122P00315000", "expiry": "2021-01-22"}, {"strike": 316, "type": "PUT", "ticker": "O:QQQ210122P00316000", "expiry": "2021-01-22"}, {"strike": 317, "type": "PUT", "ticker": "O:QQQ210122P00317000", "expiry": "2021-01-22"}, {"strike": 317.5, "type": "PUT", "ticker": "O:QQQ210122P00317500", "expiry": "2021-01-22"}, {"strike": 318, "type": "PUT", "ticker": "O:QQQ210122P00318000", "expiry": "2021-01-22"}, {"strike": 319, "type": "PUT", "ticker": "O:QQQ210122P00319000", "expiry": "2021-01-22"}, {"strike": 320, "type": "PUT", "ticker": "O:QQQ210122P00320000", "expiry": "2021-01-22"}, {"strike": 321, "type": "PUT", "ticker": "O:QQQ210122P00321000", "expiry": "2021-01-22"}, {"strike": 322, "type": "PUT", "ticker": "O:QQQ210122P00322000", "expiry": "2021-01-22"}, {"strike": 322.5, "type": "PUT", "ticker": "O:QQQ210122P00322500", "expiry": "2021-01-22"}, {"strike": 323, "type": "PUT", "ticker": "O:QQQ210122P00323000", "expiry": "2021-01-22"}, {"strike": 324, "type": "PUT", "ticker": "O:QQQ210122P00324000", "expiry": "2021-01-22"}, {"strike": 325, "type": "PUT", "ticker": "O:QQQ210122P00325000", "expiry": "2021-01-22"}, {"strike": 326, "type": "PUT", "ticker": "O:QQQ210122P00326000", "expiry": "2021-01-22"}, {"strike": 327, "type": "PUT", "ticker": "O:QQQ210122P00327000", "expiry": "2021-01-22"}, {"strike": 327.5, "type": "PUT", "ticker": "O:QQQ210122P00327500", "expiry": "2021-01-22"}, {"strike": 328, "type": "PUT", "ticker": "O:QQQ210122P00328000", "expiry": "2021-01-22"}, {"strike": 329, "type": "PUT", "ticker": "O:QQQ210122P00329000", "expiry": "2021-01-22"}, {"strike": 330, "type": "PUT", "ticker": "O:QQQ210122P00330000", "expiry": "2021-01-22"}, {"strike": 331, "type": "PUT", "ticker": "O:QQQ210122P00331000", "expiry": "2021-01-22"}, {"strike": 332, "type": "PUT", "ticker": "O:QQQ210122P00332000", "expiry": "2021-01-22"}, {"strike": 332.5, "type": "PUT", "ticker": "O:QQQ210122P00332500", "expiry": "2021-01-22"}, {"strike": 333, "type": "PUT", "ticker": "O:QQQ210122P00333000", "expiry": "2021-01-22"}, {"strike": 334, "type": "PUT", "ticker": "O:QQQ210122P00334000", "expiry": "2021-01-22"}, {"strike": 335, "type": "PUT", "ticker": "O:QQQ210122P00335000", "expiry": "2021-01-22"}, {"strike": 336, "type": "PUT", "ticker": "O:QQQ210122P00336000", "expiry": "2021-01-22"}, {"strike": 337, "type": "PUT", "ticker": "O:QQQ210122P00337000", "expiry": "2021-01-22"}, {"strike": 337.5, "type": "PUT", "ticker": "O:QQQ210122P00337500", "expiry": "2021-01-22"}, {"strike": 338, "type": "PUT", "ticker": "O:QQQ210122P00338000", "expiry": "2021-01-22"}, {"strike": 339, "type": "PUT", "ticker": "O:QQQ210122P00339000", "expiry": "2021-01-22"}, {"strike": 340, "type": "PUT", "ticker": "O:QQQ210122P00340000", "expiry": "2021-01-22"}, {"strike": 341, "type": "PUT", "ticker": "O:QQQ210122P00341000", "expiry": "2021-01-22"}, {"strike": 342, "type": "PUT", "ticker": "O:QQQ210122P00342000", "expiry": "2021-01-22"}, {"strike": 342.5, "type": "PUT", "ticker": "O:QQQ210122P00342500", "expiry": "2021-01-22"}, {"strike": 343, "type": "PUT", "ticker": "O:QQQ210122P00343000", "expiry": "2021-01-22"}, {"strike": 344, "type": "PUT", "ticker": "O:QQQ210122P00344000", "expiry": "2021-01-22"}, {"strike": 345, "type": "PUT", "ticker": "O:QQQ210122P00345000", "expiry": "2021-01-22"}, {"strike": 346, "type": "PUT", "ticker": "O:QQQ210122P00346000", "expiry": "2021-01-22"}, {"strike": 347, "type": "PUT", "ticker": "O:QQQ210122P00347000", "expiry": "2021-01-22"}, {"strike": 347.5, "type": "PUT", "ticker": "O:QQQ210122P00347500", "expiry": "2021-01-22"}, {"strike": 348, "type": "PUT", "ticker": "O:QQQ210122P00348000", "expiry": "2021-01-22"}, {"strike": 350, "type": "PUT", "ticker": "O:QQQ210122P00350000", "expiry": "2021-01-22"}, {"strike": 355, "type": "PUT", "ticker": "O:QQQ210122P00355000", "expiry": "2021-01-22"}, {"strike": 360, "type": "PUT", "ticker": "O:QQQ210122P00360000", "expiry": "2021-01-22"}, {"strike": 365, "type": "PUT", "ticker": "O:QQQ210122P00365000", "expiry": "2021-01-22"}, {"strike": 370, "type": "PUT", "ticker": "O:QQQ210122P00370000", "expiry": "2021-01-22"}, {"strike": 375, "type": "PUT", "ticker": "O:QQQ210122P00375000", "expiry": "2021-01-22"}, {"strike": 380, "type": "PUT", "ticker": "O:QQQ210122P00380000", "expiry": "2021-01-22"}, {"strike": 385, "type": "PUT", "ticker": "O:QQQ210122P00385000", "expiry": "2021-01-22"}, {"strike": 390, "type": "PUT", "ticker": "O:QQQ210122P00390000", "expiry": "2021-01-22"}, {"strike": 400, "type": "PUT", "ticker": "O:QQQ210122P00400000", "expiry": "2021-01-22"}]