[{"strike": 160, "type": "PUT", "ticker": "O:QQQ210212P00160000", "expiry": "2021-02-12"}, {"strike": 165, "type": "PUT", "ticker": "O:QQQ210212P00165000", "expiry": "2021-02-12"}, {"strike": 170, "type": "PUT", "ticker": "O:QQQ210212P00170000", "expiry": "2021-02-12"}, {"strike": 175, "type": "PUT", "ticker": "O:QQQ210212P00175000", "expiry": "2021-02-12"}, {"strike": 180, "type": "PUT", "ticker": "O:QQQ210212P00180000", "expiry": "2021-02-12"}, {"strike": 185, "type": "PUT", "ticker": "O:QQQ210212P00185000", "expiry": "2021-02-12"}, {"strike": 190, "type": "PUT", "ticker": "O:QQQ210212P00190000", "expiry": "2021-02-12"}, {"strike": 195, "type": "PUT", "ticker": "O:QQQ210212P00195000", "expiry": "2021-02-12"}, {"strike": 200, "type": "PUT", "ticker": "O:QQQ210212P00200000", "expiry": "2021-02-12"}, {"strike": 205, "type": "PUT", "ticker": "O:QQQ210212P00205000", "expiry": "2021-02-12"}, {"strike": 210, "type": "PUT", "ticker": "O:QQQ210212P00210000", "expiry": "2021-02-12"}, {"strike": 215, "type": "PUT", "ticker": "O:QQQ210212P00215000", "expiry": "2021-02-12"}, {"strike": 220, "type": "PUT", "ticker": "O:QQQ210212P00220000", "expiry": "2021-02-12"}, {"strike": 225, "type": "PUT", "ticker": "O:QQQ210212P00225000", "expiry": "2021-02-12"}, {"strike": 230, "type": "PUT", "ticker": "O:QQQ210212P00230000", "expiry": "2021-02-12"}, {"strike": 235, "type": "PUT", "ticker": "O:QQQ210212P00235000", "expiry": "2021-02-12"}, {"strike": 240, "type": "PUT", "ticker": "O:QQQ210212P00240000", "expiry": "2021-02-12"}, {"strike": 245, "type": "PUT", "ticker": "O:QQQ210212P00245000", "expiry": "2021-02-12"}, {"strike": 250, "type": "PUT", "ticker": "O:QQQ210212P00250000", "expiry": "2021-02-12"}, {"strike": 255, "type": "PUT", "ticker": "O:QQQ210212P00255000", "expiry": "2021-02-12"}, {"strike": 260, "type": "PUT", "ticker": "O:QQQ210212P00260000", "expiry": "2021-02-12"}, {"strike": 265, "type": "PUT", "ticker": "O:QQQ210212P00265000", "expiry": "2021-02-12"}, {"strike": 270, "type": "PUT", "ticker": "O:QQQ210212P00270000", "expiry": "2021-02-12"}, {"strike": 275, "type": "PUT", "ticker": "O:QQQ210212P00275000", "expiry": "2021-02-12"}, {"strike": 277.5, "type": "PUT", "ticker": "O:QQQ210212P00277500", "expiry": "2021-02-12"}, {"strike": 278, "type": "PUT", "ticker": "O:QQQ210212P00278000", "expiry": "2021-02-12"}, {"strike": 279, "type": "PUT", "ticker": "O:QQQ210212P00279000", "expiry": "2021-02-12"}, {"strike": 280, "type": "PUT", "ticker": "O:QQQ210212P00280000", "expiry": "2021-02-12"}, {"strike": 281, "type": "PUT", "ticker": "O:QQQ210212P00281000", "expiry": "2021-02-12"}, {"strike": 282, "type": "PUT", "ticker": "O:QQQ210212P00282000", "expiry": "2021-02-12"}, {"strike": 282.5, "type": "PUT", "ticker": "O:QQQ210212P00282500", "expiry": "2021-02-12"}, {"strike": 283, "type": "PUT", "ticker": "O:QQQ210212P00283000", "expiry": "2021-02-12"}, {"strike": 284, "type": "PUT", "ticker": "O:QQQ210212P00284000", "expiry": "2021-02-12"}, {"strike": 285, "type": "PUT", "ticker": "O:QQQ210212P00285000", "expiry": "2021-02-12"}, {"strike": 286, "type": "PUT", "ticker": "O:QQQ210212P00286000", "expiry": "2021-02-12"}, {"strike": 287, "type": "PUT", "ticker": "O:QQQ210212P00287000", "expiry": "2021-02-12"}, {"strike": 287.5, "type": "PUT", "ticker": "O:QQQ210212P00287500", "expiry": "2021-02-12"}, {"strike": 288, "type": "PUT", "ticker": "O:QQQ210212P00288000", "expiry": "2021-02-12"}, {"strike": 289, "type": "PUT", "ticker": "O:QQQ210212P00289000", "expiry": "2021-02-12"}, {"strike": 290, "type": "PUT", "ticker": "O:QQQ210212P00290000", "expiry": "2021-02-12"}, {"strike": 291, "type": "PUT", "ticker": "O:QQQ210212P00291000", "expiry": "2021-02-12"}, {"strike": 292, "type": "PUT", "ticker": "O:QQQ210212P00292000", "expiry": "2021-02-12"}, {"strike": 292.5, "type": "PUT", "ticker": "O:QQQ210212P00292500", "expiry": "2021-02-12"}, {"strike": 293, "type": "PUT", "ticker": "O:QQQ210212P00293000", "expiry": "2021-02-12"}, {"strike": 294, "type": "PUT", "ticker": "O:QQQ210212P00294000", "expiry": "2021-02-12"}, {"strike": 295, "type": "PUT", "ticker": "O:QQQ210212P00295000", "expiry": "2021-02-12"}, {"strike": 296, "type": "PUT", "ticker": "O:QQQ210212P00296000", "expiry": "2021-02-12"}, {"strike": 297, "type": "PUT", "ticker": "O:QQQ210212P00297000", "expiry": "2021-02-12"}, {"strike": 297.5, "type": "PUT", "ticker": "O:QQQ210212P00297500", "expiry": "2021-02-12"}, {"strike": 298, "type": "PUT", "ticker": "O:QQQ210212P00298000", "expiry": "2021-02-12"}, {"strike": 299, "type": "PUT", "ticker": "O:QQQ210212P00299000", "expiry": "2021-02-12"}, {"strike": 300, "type": "PUT", "ticker": "O:QQQ210212P00300000", "expiry": "2021-02-12"}, {"strike": 301, "type": "PUT", "ticker": "O:QQQ210212P00301000", "expiry": "2021-02-12"}, {"strike": 302, "type": "PUT", "ticker": "O:QQQ210212P00302000", "expiry": "2021-02-12"}, {"strike": 302.5, "type": "PUT", "ticker": "O:QQQ210212P00302500", "expiry": "2021-02-12"}, {"strike": 303, "type": "PUT", "ticker": "O:QQQ210212P00303000", "expiry": "2021-02-12"}, {"strike": 304, "type": "PUT", "ticker": "O:QQQ210212P00304000", "expiry": "2021-02-12"}, {"strike": 305, "type": "PUT", "ticker": "O:QQQ210212P00305000", "expiry": "2021-02-12"}, {"strike": 306, "type": "PUT", "ticker": "O:QQQ210212P00306000", "expiry": "2021-02-12"}, {"strike": 307, "type": "PUT", "ticker": "O:QQQ210212P00307000", "expiry": "2021-02-12"}, {"strike": 307.5, "type": "PUT", "ticker": "O:QQQ210212P00307500", "expiry": "2021-02-12"}, {"strike": 308, "type": "PUT", "ticker": "O:QQQ210212P00308000", "expiry": "2021-02-12"}, {"strike": 309, "type": "PUT", "ticker": "O:QQQ210212P00309000", "expiry": "2021-02-12"}, {"strike": 310, "type": "PUT", "ticker": "O:QQQ210212P00310000", "expiry": "2021-02-12"}, {"strike": 311, "type": "PUT", "ticker": "O:QQQ210212P00311000", "expiry": "2021-02-12"}, {"strike": 312, "type": "PUT", "ticker": "O:QQQ210212P00312000", "expiry": "2021-02-12"}, {"strike": 312.5, "type": "PUT", "ticker": "O:QQQ210212P00312500", "expiry": "2021-02-12"}, {"strike": 313, "type": "PUT", "ticker": "O:QQQ210212P00313000", "expiry": "2021-02-12"}, {"strike": 314, "type": "PUT", "ticker": "O:QQQ210212P00314000", "expiry": "2021-02-12"}, {"strike": 315, "type": "PUT", "ticker": "O:QQQ210212P00315000", "expiry": "2021-02-12"}, {"strike": 316, "type": "PUT", "ticker": "O:QQQ210212P00316000", "expiry": "2021-02-12"}, {"strike": 317, "type": "PUT", "ticker": "O:QQQ210212P00317000", "expiry": "2021-02-12"}, {"strike": 317.5, "type": "PUT", "ticker": "O:QQQ210212P00317500", "expiry": "2021-02-12"}, {"strike": 318, "type": "PUT", "ticker": "O:QQQ210212P00318000", "expiry": "2021-02-12"}, {"strike": 319, "type": "PUT", "ticker": "O:QQQ210212P00319000", "expiry": "2021-02-12"}, {"strike": 320, "type": "PUT", "ticker": "O:QQQ210212P00320000", "expiry": "2021-02-12"}, {"strike": 321, "type": "PUT", "ticker": "O:QQQ210212P00321000", "expiry": "2021-02-12"}, {"strike": 322, "type": "PUT", "ticker": "O:QQQ210212P00322000", "expiry": "2021-02-12"}, {"strike": 322.5, "type": "PUT", "ticker": "O:QQQ210212P00322500", "expiry": "2021-02-12"}, {"strike": 323, "type": "PUT", "ticker": "O:QQQ210212P00323000", "expiry": "2021-02-12"}, {"strike": 324, "type": "PUT", "ticker": "O:QQQ210212P00324000", "expiry": "2021-02-12"}, {"strike": 325, "type": "PUT", "ticker": "O:QQQ210212P00325000", "expiry": "2021-02-12"}, {"strike": 326, "type": "PUT", "ticker": "O:QQQ210212P00326000", "expiry": "2021-02-12"}, {"strike": 327, "type": "PUT", "ticker": "O:QQQ210212P00327000", "expiry": "2021-02-12"}, {"strike": 327.5, "type": "PUT", "ticker": "O:QQQ210212P00327500", "expiry": "2021-02-12"}, {"strike": 328, "type": "PUT", "ticker": "O:QQQ210212P00328000", "expiry": "2021-02-12"}, {"strike": 329, "type": "PUT", "ticker": "O:QQQ210212P00329000", "expiry": "2021-02-12"}, {"strike": 330, "type": "PUT", "ticker": "O:QQQ210212P00330000", "expiry": "2021-02-12"}, {"strike": 331, "type": "PUT", "ticker": "O:QQQ210212P00331000", "expiry": "2021-02-12"}, {"strike": 332, "type": "PUT", "ticker": "O:QQQ210212P00332000", "expiry": "2021-02-12"}, {"strike": 332.5, "type": "PUT", "ticker": "O:QQQ210212P00332500", "expiry": "2021-02-12"}, {"strike": 333, "type": "PUT", "ticker": "O:QQQ210212P00333000", "expiry": "2021-02-12"}, {"strike": 334, "type": "PUT", "ticker": "O:QQQ210212P00334000", "expiry": "2021-02-12"}, {"strike": 335, "type": "PUT", "ticker": "O:QQQ210212P00335000", "expiry": "2021-02-12"}, {"strike": 336, "type": "PUT", "ticker": "O:QQQ210212P00336000", "expiry": "2021-02-12"}, {"strike": 337, "type": "PUT", "ticker": "O:QQQ210212P00337000", "expiry": "2021-02-12"}, {"strike": 337.5, "type": "PUT", "ticker": "O:QQQ210212P00337500", "expiry": "2021-02-12"}, {"strike": 338, "type": "PUT", "ticker": "O:QQQ210212P00338000", "expiry": "2021-02-12"}, {"strike": 339, "type": "PUT", "ticker": "O:QQQ210212P00339000", "expiry": "2021-02-12"}, {"strike": 340, "type": "PUT", "ticker": "O:QQQ210212P00340000", "expiry": "2021-02-12"}, {"strike": 341, "type": "PUT", "ticker": "O:QQQ210212P00341000", "expiry": "2021-02-12"}, {"strike": 342, "type": "PUT", "ticker": "O:QQQ210212P00342000", "expiry": "2021-02-12"}, {"strike": 342.5, "type": "PUT", "ticker": "O:QQQ210212P00342500", "expiry": "2021-02-12"}, {"strike": 343, "type": "PUT", "ticker": "O:QQQ210212P00343000", "expiry": "2021-02-12"}, {"strike": 344, "type": "PUT", "ticker": "O:QQQ210212P00344000", "expiry": "2021-02-12"}, {"strike": 345, "type": "PUT", "ticker": "O:QQQ210212P00345000", "expiry": "2021-02-12"}, {"strike": 346, "type": "PUT", "ticker": "O:QQQ210212P00346000", "expiry": "2021-02-12"}, {"strike": 347, "type": "PUT", "ticker": "O:QQQ210212P00347000", "expiry": "2021-02-12"}, {"strike": 347.5, "type": "PUT", "ticker": "O:QQQ210212P00347500", "expiry": "2021-02-12"}, {"strike": 348, "type": "PUT", "ticker": "O:QQQ210212P00348000", "expiry": "2021-02-12"}, {"strike": 349, "type": "PUT", "ticker": "O:QQQ210212P00349000", "expiry": "2021-02-12"}, {"strike": 350, "type": "PUT", "ticker": "O:QQQ210212P00350000", "expiry": "2021-02-12"}, {"strike": 351, "type": "PUT", "ticker": "O:QQQ210212P00351000", "expiry": "2021-02-12"}, {"strike": 352, "type": "PUT", "ticker": "O:QQQ210212P00352000", "expiry": "2021-02-12"}, {"strike": 352.5, "type": "PUT", "ticker": "O:QQQ210212P00352500", "expiry": "2021-02-12"}, {"strike": 353, "type": "PUT", "ticker": "O:QQQ210212P00353000", "expiry": "2021-02-12"}, {"strike": 354, "type": "PUT", "ticker": "O:QQQ210212P00354000", "expiry": "2021-02-12"}, {"strike": 355, "type": "PUT", "ticker": "O:QQQ210212P00355000", "expiry": "2021-02-12"}, {"strike": 356, "type": "PUT", "ticker": "O:QQQ210212P00356000", "expiry": "2021-02-12"}, {"strike": 357, "type": "PUT", "ticker": "O:QQQ210212P00357000", "expiry": "2021-02-12"}, {"strike": 357.5, "type": "PUT", "ticker": "O:QQQ210212P00357500", "expiry": "2021-02-12"}, {"strike": 358, "type": "PUT", "ticker": "O:QQQ210212P00358000", "expiry": "2021-02-12"}, {"strike": 359, "type": "PUT", "ticker": "O:QQQ210212P00359000", "expiry": "2021-02-12"}, {"strike": 360, "type": "PUT", "ticker": "O:QQQ210212P00360000", "expiry": "2021-02-12"}, {"strike": 361, "type": "PUT", "ticker": "O:QQQ210212P00361000", "expiry": "2021-02-12"}, {"strike": 362.5, "type": "PUT", "ticker": "O:QQQ210212P00362500", "expiry": "2021-02-12"}, {"strike": 365, "type": "PUT", "ticker": "O:QQQ210212P00365000", "expiry": "2021-02-12"}, {"strike": 370, "type": "PUT", "ticker": "O:QQQ210212P00370000", "expiry": "2021-02-12"}, {"strike": 375, "type": "PUT", "ticker": "O:QQQ210212P00375000", "expiry": "2021-02-12"}, {"strike": 380, "type": "PUT", "ticker": "O:QQQ210212P00380000", "expiry": "2021-02-12"}, {"strike": 385, "type": "PUT", "ticker": "O:QQQ210212P00385000", "expiry": "2021-02-12"}, {"strike": 390, "type": "PUT", "ticker": "O:QQQ210212P00390000", "expiry": "2021-02-12"}, {"strike": 395, "type": "PUT", "ticker": "O:QQQ210212P00395000", "expiry": "2021-02-12"}, {"strike": 400, "type": "PUT", "ticker": "O:QQQ210212P00400000", "expiry": "2021-02-12"}, {"strike": 410, "type": "PUT", "ticker": "O:QQQ210212P00410000", "expiry": "2021-02-12"}]